fullAdder/fulladd2.v
// Full Adder by instatiating basic gates (structural modeling)

module fulladder2(A,B,Cin,S,Cout);
 input A,B,Cin;
 output S,Cout;
 wire w1,w2,w3;
 xor x1(w1,A,B);
 and a1(w2,A,B);
 xor x2(S,w1,Cin);
 and a2(w3,Cin,w1);
 or o1(Cout,w2,w3);
endmodule

fullAdder/testfull.v
// Testbench for full adder module to verify its functionality 

module testbench;
reg A,B,Cin;
wire S,Cout;

fulladder2 DUT(A,B,Cin,S,Cout);

initial
  begin
    $dumpfile("example.vcd");
    $dumpvars(0,testbench);
    $monitor($time," A=%b,B=%b,Cin=%b,S=%b,Cout=%b",A,B,Cin,S,Cout);
    #5 A=0; B=0;Cin=0;
    #5 A=0; B=0;Cin=1;
    #5 A=0; B=1;Cin=0;
    #5 A=0; B=1;Cin=1;
    #5 A=1; B=0;Cin=0;
    #5 A=1; B=0;Cin=1;
    #5 A=1; B=1;Cin=0;
    #5 A=1; B=1;Cin=1;
    #5 $finish;
  end
endmodule

fullAdder/example.vcd
$date
	Mon Dec 15 16:00:08 2025
$end
$version
	Icarus Verilog
$end
$timescale
	1s
$end
$scope module testbench $end
$var wire 1 ! S $end
$var wire 1 " Cout $end
$var reg 1 # A $end
$var reg 1 $ B $end
$var reg 1 % Cin $end
$scope module DUT $end
$var wire 1 # A $end
$var wire 1 $ B $end
$var wire 1 % Cin $end
$var wire 1 " Cout $end
$var wire 1 ! S $end
$var wire 1 & w1 $end
$var wire 1 ' w2 $end
$var wire 1 ( w3 $end
$upscope $end
$upscope $end
$enddefinitions $end
$comment Show the parameter values. $end
$dumpall
$end
#0
$dumpvars
x(
x'
x&
x%
x$
x#
x"
x!
$end
#5
0"
0!
0(
0&
0'
0%
0$
0#
#10
1!
1%
#15
1&
0%
1$
#20
1"
0!
1(
1%
#25
0"
1!
0(
0%
0$
1#
#30
1"
0!
1(
1%
#35
0(
0&
1'
0%
1$
#40
1!
1%
