16-bit counter/counter16.v
// Designing a 16-bit counter in Verilog with synchronous reset and enable signal and adding a mode for counting up or down

module counter16(clk,rst,enable,count,mode);
input clk;
input rst;
input enable;
input mode; // mode=0 for up counting, mode=1 for down counting
output reg[15:0] count=0;

always @(posedge clk) begin
  if(rst)
    count = 16'b0;
  else if(enable)
    count <= mode ? count-1 : count+1;
end
endmodule

16-bit counter/testcounter.v
module testcounter;
reg clk;
reg rst;
reg enable;
reg mode;
wire[15:0] count;

initial begin
  clk = 1'b0;
  forever #5 clk = ~clk;
end

counter16 DUT(clk,rst,enable,count,mode);

initial begin
  $dumpfile("counter16.vcd");
  $dumpvars(0,testcounter);
  $monitor($time," count is %d and rst is %d enable is %d mode is %d",count,rst,enable,mode);
  rst = 1; enable = 0; mode = 0; // start with up counting
  #5 rst = 0; enable = 1;
  #90 enable = 0;
  #20 mode = 1; // switch to down counting
  #40 enable = 1;
  #40 rst = 1;
  #10 $finish;
end
endmodule

16-bit counter/counter16.vcd
$date
	Sat Jan 17 22:24:14 2026
$end
$version
	Icarus Verilog
$end
$timescale
	1s
$end
$scope module testcounter $end
$var wire 16 ! count [15:0] $end
$var reg 1 " clk $end
$var reg 1 # enable $end
$var reg 1 $ mode $end
$var reg 1 % rst $end
$scope module DUT $end
$var wire 1 " clk $end
$var wire 1 # enable $end
$var wire 1 $ mode $end
$var wire 1 % rst $end
$var reg 16 & count [15:0] $end
$upscope $end
$upscope $end
$enddefinitions $end
$comment Show the parameter values. $end
$dumpall
$end
#0
$dumpvars
b0 &
1%
0$
0#
0"
b0 !
$end
#5
b1 !
b1 &
1#
0%
1"
#10
0"
#15
b10 !
b10 &
1"
#20
0"
#25
b11 !
b11 &
1"
#30
0"
#35
b100 !
b100 &
1"
#40
0"
#45
b101 !
b101 &
1"
#50
0"
#55
b110 !
b110 &
1"
#60
0"
#65
b111 !
b111 &
1"
#70
0"
#75
b1000 !
b1000 &
1"
#80
0"
#85
b1001 !
b1001 &
1"
#90
0"
#95
1"
0#
#100
0"
#105
1"
#110
0"
#115
1"
1$
#120
0"
#125
1"
#130
0"
#135
1"
#140
0"
#145
1"
#150
0"
#155
b1000 !
b1000 &
1"
1#
#160
0"
#165
b111 !
b111 &
1"
#170
0"
#175
b110 !
b110 &
1"
#180
0"
#185
b101 !
b101 &
1"
#190
0"
#195
b0 !
b0 &
1"
1%
