16-bit counter/counter16.v
// Designingb a 16-bit counter in Verilog with synchronous reset and enable signal

module counter16(clk,rst,enable,count);
input clk;
input rst;
input enable;
output reg[31:0] count=0;

always @(posedge clk) begin
  if(rst)
    count = 32'b0;
  else if(enable)
    count <= count+1;
end
endmodule

16-bit counter/testcounter.v
module testcounter;
reg clk;
reg rst;
reg enable;
wire[31:0] count;

initial begin
  clk = 1'b0;
  forever #5 clk = ~clk;
end

counter16 DUT(clk,rst,enable,count);

initial begin
  $dumpfile("counter16.vcd");
  $dumpvars(0,testcounter);
  $monitor($time," count is %d and rst is %d enable is %d",count,rst,enable);
  rst = 1;
  #5 rst = 0; enable = 1;
  #200 enable = 0;
  #240 enable = 1;
  #290 rst = 1;
  #10 $finish;
end
endmodule

16-bit counter/counter16.vcd
$date
	Thu Jan 15 21:58:48 2026
$end
$version
	Icarus Verilog
$end
$timescale
	1s
$end
$scope module testcounter $end
$var wire 32 ! count [31:0] $end
$var reg 1 " clk $end
$var reg 1 # enable $end
$var reg 1 $ rst $end
$scope module DUT $end
$var wire 1 " clk $end
$var wire 1 # enable $end
$var wire 1 $ rst $end
$var reg 32 % count [31:0] $end
$upscope $end
$upscope $end
$enddefinitions $end
$comment Show the parameter values. $end
$dumpall
$end
#0
$dumpvars
b0 %
1$
x#
0"
b0 !
$end
#5
b1 !
b1 %
1#
0$
1"
#10
0"
#15
b10 !
b10 %
1"
#20
0"
#25
b11 !
b11 %
1"
#30
0"
#35
b100 !
b100 %
1"
#40
0"
#45
b101 !
b101 %
1"
#50
0"
#55
b110 !
b110 %
1"
#60
0"
#65
b111 !
b111 %
1"
#70
0"
#75
b1000 !
b1000 %
1"
#80
0"
#85
b1001 !
b1001 %
1"
#90
0"
#95
b1010 !
b1010 %
1"
#100
0"
#105
b1011 !
b1011 %
1"
#110
0"
#115
b1100 !
b1100 %
1"
#120
0"
#125
b1101 !
b1101 %
1"
#130
0"
#135
b1110 !
b1110 %
1"
#140
0"
#145
b1111 !
b1111 %
1"
#150
0"
#155
b10000 !
b10000 %
1"
#160
0"
#165
b10001 !
b10001 %
1"
#170
0"
#175
b10010 !
b10010 %
1"
#180
0"
#185
b10011 !
b10011 %
1"
#190
0"
#195
b10100 !
b10100 %
1"
#200
0"
#205
1"
0#
