jk-flipflop/jkff2.v
module jkff2 (q,qbar,clk,j,k,preset,clear);
input clk,j,k,preset,clear;
output reg q;
output qbar;

assign qbar = ~q;

always @(negedge clk)
  begin
    if(preset == 0 && clear == 1) q<=1;
    else if(clear == 0 && preset == 1) q<=0;
    else if(preset==0 && clear==0) q<=1'bx;
    else begin
      case ({j,k})
        2'b00: q<=q;
        2'b01: q<=0;
        2'b10: q<=1;
        2'b11: q<=~q;
      endcase
    end
  end
endmodule

jk-flipflop/testjkff2.v
// Testbech for verifying output of jk ff

`timescale 1ns/1ps

module testjkff2;
reg clk;
reg j;
reg k;
reg preset;
reg clear;
wire q;
wire qbar;

jkff2 DUT(q,qbar,clk,j,k,preset,clear);

initial
  begin
    clk = 1'b0;
    forever #5 clk = ~ clk;
  end

initial 
  begin
    $dumpfile("jkff2.vcd");
    $dumpvars(0,testjkff2);

    $monitor($time," preset = %b , clear = %b , j=%b , k = %b | q = %b | qbar=%b",preset,clear,j,k,q,qbar);
    #10 preset =0; clear =1;
    #10 preset = 1; clear=0;
    #10 preset = 1; clear = 1; j=1; k=1;
    #10 preset = 1; clear = 1; j=1; k=0;
    #10 preset = 1; clear = 1; j=0; k=0;
    #10 preset = 1; clear = 1; j=0; k=1;
    #10 preset = 1; clear = 1; j=1; k=1;
    #20 $finish;
  end
endmodule

jk-flipflop/jkff2.vcd
$date
	Mon Jan 12 19:39:16 2026
$end
$version
	Icarus Verilog
$end
$timescale
	1ps
$end
$scope module testjkff2 $end
$var wire 1 ! qbar $end
$var wire 1 " q $end
$var reg 1 # clear $end
$var reg 1 $ clk $end
$var reg 1 % j $end
$var reg 1 & k $end
$var reg 1 ' preset $end
$scope module DUT $end
$var wire 1 # clear $end
$var wire 1 $ clk $end
$var wire 1 % j $end
$var wire 1 & k $end
$var wire 1 ' preset $end
$var wire 1 ! qbar $end
$var reg 1 " q $end
$upscope $end
$upscope $end
$enddefinitions $end
$comment Show the parameter values. $end
$dumpall
$end
#0
$dumpvars
x'
x&
x%
0$
x#
x"
x!
$end
#5000
1$
#10000
0!
1"
0$
1#
0'
#15000
1$
#20000
1!
0"
0$
0#
1'
#25000
1$
#30000
0!
1"
0$
1&
1%
1#
#35000
1$
#40000
0$
0&
#45000
1$
#50000
0$
0%
#55000
1$
#60000
1!
0"
0$
1&
#65000
1$
#70000
0!
1"
0$
1%
#75000
1$
#80000
1!
0"
0$
#85000
1$
#90000
0!
1"
0$
